tamarind/__init__.py
tamarind-0.1.1.dist-info/LICENSE
tamarind-0.1.1.dist-info/METADATA
tamarind-0.1.1.dist-info/WHEEL
tamarind-0.1.1.dist-info/top_level.txt
tamarind-0.1.1.dist-info/RECORD
