Metadata-Version: 2.1
Name: tamarind
Version: 0.1.1
Summary: More Neo4j than you can shake a cat at
Home-page: https://github.com/FitMango/tamarind
Author: Jordan Matelsky
Author-email: opensource@fitmango.com
License: MIT
Platform: UNKNOWN
Classifier: License :: OSI Approved :: MIT License
Classifier: Programming Language :: Python
Classifier: Programming Language :: Python :: 3
Classifier: Programming Language :: Python :: 3.6
Requires-Python: >=3.6.0
Provides-Extra: dev
Requires-Dist: pytest ; extra == 'dev'
Requires-Dist: pylint ; extra == 'dev'
